owntools/Common.py
owntools/CrackCode.py
owntools/Download.py
owntools/ExtractFile.py
owntools/Image.py
owntools/Loger.py
owntools/Mysql.py
owntools/Subtitles.py
owntools/Time.py
owntools/Translation.py
owntools/UncompressRAR.py
owntools/_SSH.py
owntools/__init__.py
owntools/ownEmail.py
xiuyutools-1.1.dist-info/METADATA
xiuyutools-1.1.dist-info/WHEEL
xiuyutools-1.1.dist-info/top_level.txt
xiuyutools-1.1.dist-info/RECORD
